agentberlin/__init__.py
agentberlin/_http.py
agentberlin/client.py
agentberlin/config.py
agentberlin/exceptions.py
agentberlin/py.typed
agentberlin/utils.py
agentberlin/models/__init__.py
agentberlin/models/analytics.py
agentberlin/models/brand.py
agentberlin/models/files.py
agentberlin/models/google_cse.py
agentberlin/models/gsc.py
agentberlin/models/search.py
agentberlin/models/serpapi.py
agentberlin/resources/__init__.py
agentberlin/resources/analytics.py
agentberlin/resources/brand.py
agentberlin/resources/files.py
agentberlin/resources/google_cse.py
agentberlin/resources/gsc.py
agentberlin/resources/keywords.py
agentberlin/resources/pages.py
agentberlin/resources/serpapi.py
agentberlin-0.20.0.dist-info/METADATA
agentberlin-0.20.0.dist-info/WHEEL
agentberlin-0.20.0.dist-info/licenses/LICENSE
agentberlin-0.20.0.dist-info/RECORD
