Metadata-Version: 2.4
Name: agentberlin
Version: 0.20.0
Summary: Python SDK for Agent Berlin - AI-powered SEO and AEO automation
Project-URL: Homepage, https://agentberlin.ai
Project-URL: Documentation, https://docs.agentberlin.ai/sdk/python
Project-URL: Repository, https://github.com/boat-builder/berlin
Author-email: Agent Berlin <support@agentberlin.ai>
License: MIT
License-File: LICENSE
Keywords: aeo,ai,analytics,optimization,search,seo
Classifier: Development Status :: 4 - Beta
Classifier: Intended Audience :: Developers
Classifier: License :: OSI Approved :: MIT License
Classifier: Programming Language :: Python :: 3
Classifier: Programming Language :: Python :: 3.9
Classifier: Programming Language :: Python :: 3.10
Classifier: Programming Language :: Python :: 3.11
Classifier: Programming Language :: Python :: 3.12
Classifier: Typing :: Typed
Requires-Python: >=3.9
Requires-Dist: pydantic>=2.0.0
Requires-Dist: requests>=2.28.0
Provides-Extra: dev
Requires-Dist: black>=24.0.0; extra == 'dev'
Requires-Dist: isort>=5.13.0; extra == 'dev'
Requires-Dist: mypy>=1.8.0; extra == 'dev'
Requires-Dist: pytest-cov>=4.1.0; extra == 'dev'
Requires-Dist: pytest>=8.0.0; extra == 'dev'
Requires-Dist: responses>=0.25.0; extra == 'dev'
Requires-Dist: types-requests>=2.31.0; extra == 'dev'
